core/__init__.py
core/commands/__init__.py
core/commands/base.py
core/commands/cleanup.py
core/commands/copy.py
core/commands/direct.py
core/lib/__init__.py
core/lib/constant.py
core/lib/db.py
core/lib/error.py
core/lib/hook.py
core/lib/mysql_version.py
core/lib/sql.py
core/lib/util.py
core/lib/payload/__init__.py
core/lib/payload/base.py
core/lib/payload/cleanup.py
core/lib/payload/copy.py
core/lib/payload/direct.py
core/lib/sqlparse/__init__.py
core/lib/sqlparse/create.py
core/lib/sqlparse/diff.py
core/lib/sqlparse/models.py
core/tests/__init__.py
core/tests/base_payload.py
core/tests/copy_payload.py
core/tests/error.py
core/tests/hook.py
core/tests/integration_test_lib.py
core/tests/mysql_version.py
core/tests/online_payload.py
core/tests/util.py
online_schema_change-0.0.1.post0.data/scripts/osc_cli
online_schema_change-0.0.1.post0.dist-info/DESCRIPTION.rst
online_schema_change-0.0.1.post0.dist-info/METADATA
online_schema_change-0.0.1.post0.dist-info/RECORD
online_schema_change-0.0.1.post0.dist-info/WHEEL
online_schema_change-0.0.1.post0.dist-info/metadata.json
online_schema_change-0.0.1.post0.dist-info/top_level.txt
